audiodl/__init__.py
audiodl/audio_read.py
audiodl-0.0.1.dist-info/LICENSE
audiodl-0.0.1.dist-info/METADATA
audiodl-0.0.1.dist-info/WHEEL
audiodl-0.0.1.dist-info/top_level.txt
audiodl-0.0.1.dist-info/zip-safe
audiodl-0.0.1.dist-info/RECORD
